argkit/__init__.py
argkit/cli.py
argkit/core.py
argkit-0.1.5.dist-info/licenses/LICENSE
argkit-0.1.5.dist-info/METADATA
argkit-0.1.5.dist-info/WHEEL
argkit-0.1.5.dist-info/entry_points.txt
argkit-0.1.5.dist-info/top_level.txt
argkit-0.1.5.dist-info/RECORD
