Metadata-Version: 2.4
Name: argkit
Version: 0.1.5
Summary: Connecting an argument parser and a callable.
Author: Jiyuan Yang
License-Expression: MIT
Project-URL: Homepage, https://github.com/ygjiyn/argkit_project
Project-URL: Issues, https://github.com/ygjiyn/argkit_project/issues
Classifier: Programming Language :: Python :: 3
Classifier: Operating System :: OS Independent
Requires-Python: >=3.9
License-File: LICENSE
Dynamic: license-file
